MANIFEST.in
README.md
bcftools.tar.bz2
htslib.tar.bz2
pyproject.toml
requirements.txt
samtools.tar.bz2
setup.py
scripts/xsamtools
tests/infra/__init__.py
xsamtools/__init__.py
xsamtools/cram.py
xsamtools/gs_utils.py
xsamtools/pipes.py
xsamtools/samtools.py
xsamtools/utils.py
xsamtools/vcf.py
xsamtools/version.py
xsamtools.egg-info/PKG-INFO
xsamtools.egg-info/SOURCES.txt
xsamtools.egg-info/dependency_links.txt
xsamtools.egg-info/not-zip-safe
xsamtools.egg-info/requires.txt
xsamtools.egg-info/top_level.txt
xsamtools/cli/__init__.py
xsamtools/cli/cram.py
xsamtools/cli/vcf.py