Metadata-Version: 2.1
Name: xsamtools
Version: 0.5.9
Summary: Lightly modified versions of samtools, htslib, and bcftools.
Home-page: https://github.com/xbrianh/xsamtools.git
Author: Brian Hannafious
Author-email: bhannafi@ucsc.edu
License: MIT
Platform: MacOS X
Platform: Posix
Classifier: Intended Audience :: Developers
Classifier: License :: OSI Approved :: MIT License
Classifier: Programming Language :: Python :: 3.7
